SpecAISeg/__init__.py
SpecAISeg/datasets.py
SpecAISeg/plotting.py
SpecAISeg/utils.py
SpecAISeg/whitening.py
SpecAISeg/_utils/ReadHSI.py
SpecAISeg/_utils/__init__.py
SpecAISeg/metrics/__init__.py
SpecAISeg/metrics/_metrics.py
SpecAISeg/metrics/distance.py
SpecAISeg/metrics/frc.py
SpecAISeg/metrics/misc.py
SpecAISeg/metrics/zeb.py
SpecAISeg/models/__init__.py
SpecAISeg/models/_slic_wrap.py
SpecAISeg/models/classifiers.py
SpecAISeg/models/dimreds.py
SpecAISeg/models/segmenters.py
SpecAISeg/models/_classifiers/__init__.py
SpecAISeg/models/_classifiers/speclib.py
SpecAISeg/models/_classifiers/trainedmodels.py
SpecAISeg/uq/__init__.py
SpecAISeg/uq/_uq_metric.py
SpecAISeg/uq/suqs.py
SpecAISeg-1.0.3.dist-info/LICENSE.txt
SpecAISeg-1.0.3.dist-info/METADATA
SpecAISeg-1.0.3.dist-info/WHEEL
SpecAISeg-1.0.3.dist-info/top_level.txt
SpecAISeg-1.0.3.dist-info/RECORD
